[{"line":1,"elements":[{"start_timestamp":"2023-04-30T04:32:52.043Z","before":[{"result":{"duration":2020461400,"status":"passed"},"match":{"location":"AllHooks.Hooks.setup2()"}},{"result":{"duration":15135879600,"status":"passed"},"match":{"location":"AllHooks.Hooks.setUp()"}}],"line":8,"name":"The user is able to navigate to a page having Arrays in Python Topic","description":"","id":"evaluate-arrays-module;the-user-is-able-to-navigate-to-a-page-having-arrays-in-python-topic","after":[{"result":{"duration":6039600,"status":"passed"},"match":{"location":"AllHooks.Hooks.tearDown(io.cucumber.java.Scenario)"}}],"type":"scenario","keyword":"Scenario","steps":[{"result":{"duration":3649348100,"status":"passed"},"line":9,"name":"User click on get started button on array module and navigate to array page","match":{"location":"stepdefinitions.ArraysStepdf.user_click_on_get_started_button_on_array_module_and_navigate_to_array_page()"},"keyword":"Given "},{"result":{"duration":346727000,"status":"passed"},"line":10,"name":"User click on Arrays in Python Topic and navigate to arrays in python page","match":{"location":"stepdefinitions.ArraysStepdf.user_click_on_arrays_in_python_topic_and_navigate_to_arrays_in_python_page()"},"keyword":"When "}],"tags":[{"name":"@tag6"}]},{"start_timestamp":"2023-04-30T04:33:13.527Z","before":[{"result":{"duration":1996200,"status":"passed"},"match":{"location":"AllHooks.Hooks.setup2()"}},{"result":{"duration":992900,"status":"passed"},"match":{"location":"AllHooks.Hooks.setUp()"}}],"line":20,"name":"User is able to navigate to tryeditor page and run valid python code","description":"","id":"evaluate-arrays-module;user-is-able-to-navigate-to-tryeditor-page-and-run-valid-python-code;;2","after":[{"result":{"status":"passed"},"match":{"location":"AllHooks.Hooks.tearDown(io.cucumber.java.Scenario)"}}],"type":"scenario","keyword":"Scenario Outline","steps":[{"result":{"duration":621236200,"status":"passed"},"line":14,"name":"User click on Try here button on Arrays in Python page and navigate to try edidor page","match":{"location":"stepdefinitions.ArraysStepdf.user_click_on_try_here_button_on_arrays_in_python_page()"},"keyword":"Given "},{"result":{"duration":2134922700,"status":"passed"},"line":15,"name":"The user enter valid python code in tryEditor from sheet \"Sheet1\" and 0","match":{"arguments":[{"val":"\"Sheet1\"","offset":57},{"val":"0","offset":70}],"location":"stepdefinitions.ArraysStepdf.the_user_enter_valid_python_code_in_try_editor_from_sheet_and(java.lang.String,java.lang.Integer)"},"keyword":"When "},{"result":{"duration":1100114500,"status":"passed"},"line":16,"name":"User click on run button","match":{"location":"stepdefinitions.ArraysStepdf.user_click_on_run_button()"},"keyword":"And "},{"result":{"duration":48987000,"status":"passed"},"line":17,"name":"User should be presented with run result","match":{"location":"stepdefinitions.ArraysStepdf.user_should_be_presented_with_run_result()"},"keyword":"Then "}],"tags":[{"name":"@tag7"}]},{"start_timestamp":"2023-04-30T04:33:17.532Z","before":[{"result":{"duration":1998100,"status":"passed"},"match":{"location":"AllHooks.Hooks.setup2()"}},{"result":{"duration":999500,"status":"passed"},"match":{"location":"AllHooks.Hooks.setUp()"}}],"line":30,"name":"User is able to navigate to tryeditor page and run invalid python code","description":"","id":"evaluate-arrays-module;user-is-able-to-navigate-to-tryeditor-page-and-run-invalid-python-code;;2","after":[{"result":{"status":"passed"},"match":{"location":"AllHooks.Hooks.tearDown(io.cucumber.java.Scenario)"}}],"type":"scenario","keyword":"Scenario Outline","steps":[{"result":{"duration":557400500,"status":"passed"},"line":24,"name":"User click on Try here button on Arrays in Python page and navigate to try edidor page","match":{"location":"stepdefinitions.ArraysStepdf.user_click_on_try_here_button_on_arrays_in_python_page()"},"keyword":"Given "},{"result":{"duration":131045200,"status":"passed"},"line":25,"name":"The user enter invalid python code in tryEditor from sheet \"Sheet1\" and 1","match":{"arguments":[{"val":"\"Sheet1\"","offset":59},{"val":"1","offset":72}],"location":"stepdefinitions.ArraysStepdf.the_user_enter_invalid_python_code_in_try_editor_from_sheet_and(java.lang.String,java.lang.Integer)"},"keyword":"When "},{"result":{"duration":1065811500,"status":"passed"},"line":26,"name":"User click on run button","match":{"location":"stepdefinitions.ArraysStepdf.user_click_on_run_button()"},"keyword":"And "},{"result":{"duration":611074600,"status":"passed"},"line":27,"name":"User should get alert message","match":{"location":"stepdefinitions.ArraysStepdf.alert_should_be_present()"},"keyword":"Then "}],"tags":[{"name":"@tag7"}]},{"start_timestamp":"2023-04-30T04:33:19.915Z","before":[{"result":{"duration":5627200,"status":"passed"},"match":{"location":"AllHooks.Hooks.setup2()"}},{"result":{"status":"passed"},"match":{"location":"AllHooks.Hooks.setUp()"}}],"line":40,"name":"User is able to navigate to tryeditor page and run valid python code","description":"","id":"evaluate-arrays-module;user-is-able-to-navigate-to-tryeditor-page-and-run-valid-python-code;;2","after":[{"result":{"status":"passed"},"match":{"location":"AllHooks.Hooks.tearDown(io.cucumber.java.Scenario)"}}],"type":"scenario","keyword":"Scenario Outline","steps":[{"result":{"duration":427708000,"status":"passed"},"line":33,"name":"User click on Arrays Using List topic","match":{"location":"stepdefinitions.ArraysStepdf.user_click_on_arrays_using_list_topic()"},"keyword":"Given "},{"result":{"duration":466309800,"status":"passed"},"line":34,"name":"click Try here button and navigate to try edidor page","match":{"location":"stepdefinitions.ArraysStepdf.click_try_here_button_and_navigate_to_try_edidor_page()"},"keyword":"And "},{"result":{"duration":348742300,"status":"passed"},"line":35,"name":"The user enter valid python code in tryEditor from sheet \"Sheet1\" and 0","match":{"arguments":[{"val":"\"Sheet1\"","offset":57},{"val":"0","offset":70}],"location":"stepdefinitions.ArraysStepdf.the_user_enter_valid_python_code_in_try_editor_from_sheet_and(java.lang.String,java.lang.Integer)"},"keyword":"When "},{"result":{"duration":1125904700,"status":"passed"},"line":36,"name":"User click on run button","match":{"location":"stepdefinitions.ArraysStepdf.user_click_on_run_button()"},"keyword":"And "},{"result":{"duration":66344900,"status":"passed"},"line":37,"name":"User should be presented with run result","match":{"location":"stepdefinitions.ArraysStepdf.user_should_be_presented_with_run_result()"},"keyword":"Then "}],"tags":[{"name":"@tag8"}]},{"start_timestamp":"2023-04-30T04:33:22.362Z","before":[{"result":{"duration":12197800,"status":"passed"},"match":{"location":"AllHooks.Hooks.setup2()"}},{"result":{"duration":1251500,"status":"passed"},"match":{"location":"AllHooks.Hooks.setUp()"}}],"line":51,"name":"User is able to navigate to tryeditor page and run invalid python code","description":"","id":"evaluate-arrays-module;user-is-able-to-navigate-to-tryeditor-page-and-run-invalid-python-code;;2","after":[{"result":{"status":"passed"},"match":{"location":"AllHooks.Hooks.tearDown(io.cucumber.java.Scenario)"}}],"type":"scenario","keyword":"Scenario Outline","steps":[{"result":{"duration":183943100,"status":"passed"},"line":44,"name":"User click on Arrays Using List topic","match":{"location":"stepdefinitions.ArraysStepdf.user_click_on_arrays_using_list_topic()"},"keyword":"Given "},{"result":{"duration":284806800,"status":"passed"},"line":45,"name":"click Try here button and navigate to try edidor page","match":{"location":"stepdefinitions.ArraysStepdf.click_try_here_button_and_navigate_to_try_edidor_page()"},"keyword":"And "},{"result":{"duration":89524900,"status":"passed"},"line":46,"name":"The user enter invalid python code in tryEditor from sheet \"Sheet1\" and 1","match":{"arguments":[{"val":"\"Sheet1\"","offset":59},{"val":"1","offset":72}],"location":"stepdefinitions.ArraysStepdf.the_user_enter_invalid_python_code_in_try_editor_from_sheet_and(java.lang.String,java.lang.Integer)"},"keyword":"When "},{"result":{"duration":1071564400,"status":"passed"},"line":47,"name":"User click on run button","match":{"location":"stepdefinitions.ArraysStepdf.user_click_on_run_button()"},"keyword":"And "},{"result":{"duration":62489600,"status":"passed"},"line":48,"name":"User should get alert message","match":{"location":"stepdefinitions.ArraysStepdf.alert_should_be_present()"},"keyword":"Then "}],"tags":[{"name":"@tag8"}]},{"start_timestamp":"2023-04-30T04:33:24.075Z","before":[{"result":{"duration":17798000,"status":"passed"},"match":{"location":"AllHooks.Hooks.setup2()"}},{"result":{"duration":3173600,"status":"passed"},"match":{"location":"AllHooks.Hooks.setUp()"}}],"line":62,"name":"User is able to navigate to tryeditor page and run valid python code","description":"","id":"evaluate-arrays-module;user-is-able-to-navigate-to-tryeditor-page-and-run-valid-python-code;;2","after":[{"result":{"status":"passed"},"match":{"location":"AllHooks.Hooks.tearDown(io.cucumber.java.Scenario)"}}],"type":"scenario","keyword":"Scenario Outline","steps":[{"result":{"duration":212499900,"status":"passed"},"line":55,"name":"User click on basic Operations in Lists","match":{"location":"stepdefinitions.ArraysStepdf.user_click_on_basic_operations_in_lists()"},"keyword":"Given "},{"result":{"duration":224715000,"status":"passed"},"line":56,"name":"click Try here button and navigate to try edidor page","match":{"location":"stepdefinitions.ArraysStepdf.click_try_here_button_and_navigate_to_try_edidor_page()"},"keyword":"And "},{"result":{"duration":156826400,"status":"passed"},"line":57,"name":"The user enter valid python code in tryEditor from sheet \"Sheet1\" and 0","match":{"arguments":[{"val":"\"Sheet1\"","offset":57},{"val":"0","offset":70}],"location":"stepdefinitions.ArraysStepdf.the_user_enter_valid_python_code_in_try_editor_from_sheet_and(java.lang.String,java.lang.Integer)"},"keyword":"When "},{"result":{"duration":1073288900,"status":"passed"},"line":58,"name":"User click on run button","match":{"location":"stepdefinitions.ArraysStepdf.user_click_on_run_button()"},"keyword":"And "},{"result":{"duration":69438500,"status":"passed"},"line":59,"name":"User should be presented with run result","match":{"location":"stepdefinitions.ArraysStepdf.user_should_be_presented_with_run_result()"},"keyword":"Then "}],"tags":[{"name":"@tag9"}]},{"start_timestamp":"2023-04-30T04:33:25.849Z","before":[{"result":{"status":"passed"},"match":{"location":"AllHooks.Hooks.setup2()"}},{"result":{"duration":1202700,"status":"passed"},"match":{"location":"AllHooks.Hooks.setUp()"}}],"line":73,"name":"User is able to navigate to tryeditor page and run invalid python code","description":"","id":"evaluate-arrays-module;user-is-able-to-navigate-to-tryeditor-page-and-run-invalid-python-code;;2","after":[{"result":{"duration":984100,"status":"passed"},"match":{"location":"AllHooks.Hooks.tearDown(io.cucumber.java.Scenario)"}}],"type":"scenario","keyword":"Scenario Outline","steps":[{"result":{"duration":158497800,"status":"passed"},"line":66,"name":"User click on basic Operations in Lists","match":{"location":"stepdefinitions.ArraysStepdf.user_click_on_basic_operations_in_lists()"},"keyword":"Given "},{"result":{"duration":246435900,"status":"passed"},"line":67,"name":"click Try here button and navigate to try edidor page","match":{"location":"stepdefinitions.ArraysStepdf.click_try_here_button_and_navigate_to_try_edidor_page()"},"keyword":"And "},{"result":{"duration":94918400,"status":"passed"},"line":68,"name":"The user enter invalid python code in tryEditor from sheet \"Sheet1\" and 1","match":{"arguments":[{"val":"\"Sheet1\"","offset":59},{"val":"1","offset":72}],"location":"stepdefinitions.ArraysStepdf.the_user_enter_invalid_python_code_in_try_editor_from_sheet_and(java.lang.String,java.lang.Integer)"},"keyword":"When "},{"result":{"duration":1065967200,"status":"passed"},"line":69,"name":"User click on run button","match":{"location":"stepdefinitions.ArraysStepdf.user_click_on_run_button()"},"keyword":"And "},{"result":{"duration":75549400,"status":"passed"},"line":70,"name":"User should get alert message","match":{"location":"stepdefinitions.ArraysStepdf.alert_should_be_present()"},"keyword":"Then "}],"tags":[{"name":"@tag9"}]},{"start_timestamp":"2023-04-30T04:33:27.528Z","before":[{"result":{"duration":3998200,"status":"passed"},"match":{"location":"AllHooks.Hooks.setup2()"}},{"result":{"duration":1000100,"status":"passed"},"match":{"location":"AllHooks.Hooks.setUp()"}}],"line":85,"name":"User is able to navigate to tryeditor page and run valid python code","description":"","id":"evaluate-arrays-module;user-is-able-to-navigate-to-tryeditor-page-and-run-valid-python-code;;2","after":[{"result":{"duration":1030900,"status":"passed"},"match":{"location":"AllHooks.Hooks.tearDown(io.cucumber.java.Scenario)"}}],"type":"scenario","keyword":"Scenario Outline","steps":[{"result":{"duration":375152300,"status":"passed"},"line":78,"name":"User click on Applications of Array","match":{"location":"stepdefinitions.ArraysStepdf.user_click_on_applications_of_array()"},"keyword":"Given "},{"result":{"duration":473934300,"status":"passed"},"line":79,"name":"click Try here button and navigate to try edidor page","match":{"location":"stepdefinitions.ArraysStepdf.click_try_here_button_and_navigate_to_try_edidor_page()"},"keyword":"And "},{"result":{"duration":174035700,"status":"passed"},"line":80,"name":"The user enter valid python code in tryEditor from sheet \"Sheet1\" and 0","match":{"arguments":[{"val":"\"Sheet1\"","offset":57},{"val":"0","offset":70}],"location":"stepdefinitions.ArraysStepdf.the_user_enter_valid_python_code_in_try_editor_from_sheet_and(java.lang.String,java.lang.Integer)"},"keyword":"When "},{"result":{"duration":1088198000,"status":"passed"},"line":81,"name":"User click on run button","match":{"location":"stepdefinitions.ArraysStepdf.user_click_on_run_button()"},"keyword":"And "},{"result":{"duration":50443200,"status":"passed"},"line":82,"name":"User should be presented with run result","match":{"location":"stepdefinitions.ArraysStepdf.user_should_be_presented_with_run_result()"},"keyword":"Then "}],"tags":[{"name":"@tag10"}]},{"start_timestamp":"2023-04-30T04:33:29.707Z","before":[{"result":{"duration":2421500,"status":"passed"},"match":{"location":"AllHooks.Hooks.setup2()"}},{"result":{"duration":2551500,"status":"passed"},"match":{"location":"AllHooks.Hooks.setUp()"}}],"line":95,"name":"User is able to navigate to tryeditor page and run valid python code","description":"","id":"evaluate-arrays-module;user-is-able-to-navigate-to-tryeditor-page-and-run-valid-python-code;;2","after":[{"result":{"duration":509500,"status":"passed"},"match":{"location":"AllHooks.Hooks.tearDown(io.cucumber.java.Scenario)"}}],"type":"scenario","keyword":"Scenario Outline","steps":[{"result":{"duration":291363800,"status":"passed"},"line":88,"name":"User click on Applications of Array","match":{"location":"stepdefinitions.ArraysStepdf.user_click_on_applications_of_array()"},"keyword":"Given "},{"result":{"duration":1704679700,"status":"passed"},"line":89,"name":"click Try here button and navigate to try edidor page","match":{"location":"stepdefinitions.ArraysStepdf.click_try_here_button_and_navigate_to_try_edidor_page()"},"keyword":"And "},{"result":{"duration":103993500,"status":"passed"},"line":90,"name":"The user enter invalid python code in tryEditor from sheet \"Sheet1\" and 1","match":{"arguments":[{"val":"\"Sheet1\"","offset":59},{"val":"1","offset":72}],"location":"stepdefinitions.ArraysStepdf.the_user_enter_invalid_python_code_in_try_editor_from_sheet_and(java.lang.String,java.lang.Integer)"},"keyword":"When "},{"result":{"duration":1057972500,"status":"passed"},"line":91,"name":"User click on run button","match":{"location":"stepdefinitions.ArraysStepdf.user_click_on_run_button()"},"keyword":"And "},{"result":{"duration":60406300,"status":"passed"},"line":92,"name":"User should get alert message","match":{"location":"stepdefinitions.ArraysStepdf.alert_should_be_present()"},"keyword":"Then "}],"tags":[{"name":"@tag10"}]}],"name":"Evaluate arrays module","description":"","id":"evaluate-arrays-module","keyword":"Feature","uri":"file:src/test/resources/Features/Arrays.feature","tags":[]}]